LICENSE
README.md
setup.cfg
setup.py
lasertools_pulsedispersion/__init__.py
lasertools_pulsedispersion/dispersion_model.py
lasertools_pulsedispersion.egg-info/PKG-INFO
lasertools_pulsedispersion.egg-info/SOURCES.txt
lasertools_pulsedispersion.egg-info/dependency_links.txt
lasertools_pulsedispersion.egg-info/requires.txt
lasertools_pulsedispersion.egg-info/top_level.txt
lasertools_pulsedispersion/models/__init__.py
lasertools_pulsedispersion/models/arbitrary_index.py
lasertools_pulsedispersion/models/arbitrary_phase.py
lasertools_pulsedispersion/models/base.py
lasertools_pulsedispersion/models/numeric_gdd.py
lasertools_pulsedispersion/models/numeric_phase.py
lasertools_pulsedispersion/models/sellmeier_index.py